subzuf.py
subzuf-2023.1.0.dist-info/METADATA
subzuf-2023.1.0.dist-info/WHEEL
subzuf-2023.1.0.dist-info/entry_points.txt
subzuf-2023.1.0.dist-info/top_level.txt
subzuf-2023.1.0.dist-info/RECORD
